secateur/__init__.py
secateur/adapters.py
secateur/analytics.py
secateur/codec.py
secateur/commands.py
secateur/config.py
secateur/logger.py
secateur/schema.json
secateur/secateur.py
secateur-0.2.3.dist-info/LICENSE
secateur-0.2.3.dist-info/METADATA
secateur-0.2.3.dist-info/WHEEL
secateur-0.2.3.dist-info/top_level.txt
secateur-0.2.3.dist-info/RECORD
