Metadata-Version: 2.1
Name: secateur
Version: 0.2.3
Summary: A framework for migrating relational databases to document-oriented databases
Home-page: https://github.com/darentydarenty/secateur
Author: Daniil Somov
Author-email: darenty4@gmail.com
License: UNKNOWN
Platform: UNKNOWN
Classifier: Programming Language :: Python :: 3
Classifier: License :: OSI Approved :: MIT License
Classifier: Operating System :: OS Independent
Requires-Python: >=3.6
Requires-Dist: jsonschema
Requires-Dist: jinja2
Requires-Dist: sqlalchemy
Requires-Dist: pymongo
Requires-Dist: tqdm
